invtorch/__init__.py
invtorch/random.py
invtorch/autograd/__init__.py
invtorch/autograd/grad_mode.py
invtorch/nn/__init__.py
invtorch/nn/modules/__init__.py
invtorch/nn/modules/batchnorm.py
invtorch/nn/modules/container.py
invtorch/nn/modules/conv.py
invtorch/nn/modules/flatten.py
invtorch/nn/modules/linear.py
invtorch/nn/modules/module.py
invtorch/nn/modules/padding.py
invtorch/nn/modules/pixelshuffle.py
invtorch/utils/__init__.py
invtorch/utils/checkpoint.py
invtorch/utils/parametrizations.py
invtorch/utils/tools.py
invtorch-0.5.0.dist-info/LICENSE
invtorch-0.5.0.dist-info/METADATA
invtorch-0.5.0.dist-info/WHEEL
invtorch-0.5.0.dist-info/top_level.txt
invtorch-0.5.0.dist-info/zip-safe
invtorch-0.5.0.dist-info/RECORD
