Metadata-Version: 2.1
Name: invtorch
Version: 0.5.0
Summary: InvTorch: Memory-Efficient Invertible Functions
Home-page: http://github.com/xmodar/invtorch
Author: Modar M. Alfadly
Author-email: modar.alfadly@gmail.com
License: Apache-2.0
Keywords: deep learning,pytorch,ai
Platform: UNKNOWN
Classifier: Environment :: Console
Classifier: Natural Language :: English
Classifier: Development Status :: 3 - Alpha
Classifier: Intended Audience :: Developers
Classifier: Topic :: Scientific/Engineering :: Artificial Intelligence
Classifier: Topic :: Scientific/Engineering :: Image Recognition
Classifier: Topic :: Scientific/Engineering :: Information Analysis
Classifier: License :: OSI Approved :: Apache Software License
Classifier: Operating System :: OS Independent
Classifier: Programming Language :: Python :: 3
Classifier: Programming Language :: Python :: 3.6
Classifier: Programming Language :: Python :: 3.7
Classifier: Programming Language :: Python :: 3.8
Classifier: Programming Language :: Python :: 3.9
Requires-Python: >=3.6
License-File: LICENSE
Requires-Dist: torch (>=1.10.0)
